{"type":"PR","pr":{"number":116,"head":"85e3f449c2505955c2a3615abae1c779663d5f74"},"user":"feliped.cardoso","status":"pending_publish","branch":"cms/escada-de-portaló-verifique-se-o-seu-navio-está-de-acordo-com-as-recomendações-e-práticas-internacionais","collection":"blog","title":"Escada de portaló: verifique se o seu navio está de acordo com as recomendações e práticas internacionais.","description":"No Description!","objects":{"entry":{"path":"content/artigos/escada-de-portaló-verifique-se-o-seu-navio-está-de-acordo-com-as-recomendações-e-práticas-internacionais.md","sha":"cdc015afbd80e9b91bd577079165c1a43f022ed8"},"files":[]},"timeStamp":"2018-11-27T14:31:52.778Z"}